{
  "transactions": [
    {
      "description": "Salário",
      "amount": 5000,
      "type": "expense",
      "category": "Alimentação",
      "date": "2025-08-08",
      "recipient": "",
      "attachments": [
        "1Henrique.png"
      ],
      "id": 1
    },
    {
      "id": 3,
      "description": "Supermercado",
      "amount": 450,
      "type": "expense",
      "category": "Alimentação",
      "date": "2023-10-15",
      "recipient": "Extra Supermercados",
      "attachments": []
    },
    {
      "id": 4,
      "description": "Freelance",
      "amount": 1200,
      "type": "income",
      "category": "Trabalho",
      "date": "2023-10-20",
      "recipient": "Empresa XYZ",
      "attachments": []
    },
    {
      "description": "teste",
      "amount": 100,
      "type": "income",
      "category": "entertainment",
      "date": "2025-08-01",
      "id": 5
    },
    {
      "description": "mercado",
      "amount": 250,
      "type": "expense",
      "category": "groceries",
      "date": "2025-08-02",
      "id": 6
    }
  ],
  "profile": [
    {
      "name": "hnrq",
      "email": "diretor@teste.com",
      "password": "123456",
      "id": 1
    }
  ],
  "categories": [
    "Alimentação",
    "Transporte",
    "Moradia",
    "Lazer",
    "Saúde",
    "Educação",
    "Trabalho",
    "Outros"
  ]
}