{
  "transactions": [
    {
      "description": "Rango do baum",
      "amount": 600,
      "type": "expense",
      "category": "groceries",
      "date": "2025-08-03",
      "id": 2
    },
    {
      "description": "Teste123",
      "amount": 200,
      "type": "income",
      "category": "education",
      "date": "2025-06-13",
      "recipient": "",
      "attachments": [],
      "id": 3
    },
    {
      "description": "teste2",
      "amount": 250,
      "type": "expense",
      "category": "bills",
      "date": "2025-08-03",
      "id": 4
    }
  ],
  "profile": [
    {
      "name": "SILVIO CELSO DA SILVA",
      "email": "silvioand1@gmail.com",
      "password": "123456",
      "balance": 0,
      "id": 1
    }
  ],
  "categories": [
    "Alimentação",
    "Transporte",
    "Moradia",
    "Lazer",
    "Saúde",
    "Educação",
    "Trabalho",
    "Outros"
  ]
}